{
    "Husky022": {
        "Arch_Patterns": "https://github.com/Husky022/Arch_Patterns",
        "Bot": "https://github.com/Husky022/Bot",
        "GB_Python": "https://github.com/Husky022/GB_Python",
        "geekbrains": "https://github.com/Husky022/geekbrains",
        "geekshop": "https://github.com/Husky022/geekshop",
        "hassio": "https://github.com/Husky022/hassio",
        "Intellegia": "https://github.com/Husky022/Intellegia",
        "intergalactic": "https://github.com/Husky022/intergalactic",
        "IQworkers": "https://github.com/Husky022/IQworkers",
        "js": "https://github.com/Husky022/js",
        "js2": "https://github.com/Husky022/js2",
        "project": "https://github.com/Husky022/project",
        "python_algos_gb": "https://github.com/Husky022/python_algos_gb",
        "Python_CSA": "https://github.com/Husky022/Python_CSA",
        "repo-github": "https://github.com/Husky022/repo-github",
        "repo22": "https://github.com/Husky022/repo22",
        "Scraping": "https://github.com/Husky022/Scraping"
    }
}